downloads3key/__init__.py
downloads3key/__main__.py
downloads3key/cli.py
downloads3key-2.7.2.dist-info/LICENSE.txt
downloads3key-2.7.2.dist-info/METADATA
downloads3key-2.7.2.dist-info/WHEEL
downloads3key-2.7.2.dist-info/entry_points.txt
downloads3key-2.7.2.dist-info/top_level.txt
downloads3key-2.7.2.dist-info/RECORD
